aioredisgraph/__init__.py
aioredisgraph/edge.py
aioredisgraph/exceptions.py
aioredisgraph/execution_plan.py
aioredisgraph/graph.py
aioredisgraph/node.py
aioredisgraph/path.py
aioredisgraph/query_result.py
aioredisgraph/util.py
aioredisgraph-2.4.4.dist-info/LICENSE
aioredisgraph-2.4.4.dist-info/WHEEL
aioredisgraph-2.4.4.dist-info/METADATA
aioredisgraph-2.4.4.dist-info/RECORD
